[
  {
    "ts": "2026-03-23T06:40:10",
    "start": "06:16",
    "end": "06:40",
    "original": "Diskussion OpenClaw KSPLEN",
    "corrected": "Diskussion Vortag mit OpenClaw KSPLAW"
  },
  {
    "ts": "2026-03-23T16:16:06",
    "start": "15:53",
    "end": "15:54",
    "original": "Analysen in Arena AI INSUAI",
    "corrected": "Ansehen Youtube-Videos RAYTYT"
  },
  {
    "ts": "2026-03-23T16:17:24",
    "start": "16:07",
    "end": "16:08",
    "original": "div. Surfen INSUSU",
    "corrected": "Bearb. Essensplan (gegessen / Lokalsuche / Konsumation / Einkaufsliste) LEEPLS"
  },
  {
    "ts": "2026-03-23T16:22:14",
    "start": "15:54",
    "end": "15:56",
    "original": "Analysen in Arena AI INSUAI",
    "corrected": "Befragung Arena.AI INSUSU"
  },
  {
    "ts": "2026-03-23T17:34:31",
    "start": "16:33",
    "end": "16:41",
    "original": "div. Surfen INSUSU",
    "corrected": "Analyse DJ Break Thinking Frequencies RAAFAN"
  },
  {
    "ts": "2026-03-23T17:34:43",
    "start": "16:33",
    "end": "16:47",
    "original": "div. Surfen INSUSU",
    "corrected": "Analyse DJ Break Thinking Frequencies RAAFAN"
  },
  {
    "ts": "2026-03-23T17:36:38",
    "start": "16:52",
    "end": "17:12",
    "original": "Diskussion OpenClaw KSPLEN",
    "corrected": "Diskussion Planungsfehler mit OpenClaw KSPLEN"
  },
  {
    "ts": "2026-03-23T17:36:59",
    "start": "16:52",
    "end": "17:13",
    "original": "Diskussion OpenClaw KSPLEN",
    "corrected": "Diskussion Planungsfehler mit OpenClaw KSPLEN"
  },
  {
    "ts": "2026-03-23T17:37:30",
    "start": "17:16",
    "end": "17:20",
    "original": "Diskussion OpenClaw KSPLEN",
    "corrected": "Reparatur Planungsfehler mit OpenClaw KSPLEN"
  },
  {
    "ts": "2026-03-23T17:37:49",
    "start": "17:23",
    "end": "17:24",
    "original": "Diskussion OpenClaw KSPLEN",
    "corrected": "Diskussion Planungsfehler mit OpenClaw KSPLEN"
  },
  {
    "ts": "2026-03-23T19:43:52",
    "start": "19:40",
    "end": "19:42",
    "original": "Diskussion OpenClaw KSPLEN",
    "corrected": "Diskussion Planungsfehler mit OpenClaw KSPLEN"
  },
  {
    "ts": "2026-03-23T19:43:58",
    "start": "19:40",
    "end": "19:43",
    "original": "Diskussion OpenClaw KSPLEN",
    "corrected": "Diskussion Planungsfehler mit OpenClaw KSPLEN"
  },
  {
    "ts": "2026-03-23T23:32:03",
    "start": "23:25",
    "end": "23:29",
    "original": "Sonstige PC-Nutzung",
    "corrected": "Ansehen div. Bilder und Videos"
  },
  {
    "ts": "2026-03-23T23:32:09",
    "start": "23:29",
    "end": "23:32",
    "original": "Erfassung Ablauf KSPLEA",
    "corrected": "Nacherfassung Ablauf KSPLNA"
  }
]